myfoobar.cpython-38-x86_64-linux-gnu.so
myfoobar.pyi
myfoobar.cpython-39-x86_64-linux-gnu.so
myfoobar.cpython-310-x86_64-linux-gnu.so
myfoobar.cpython-37m-x86_64-linux-gnu.so
myfoobar-0.0.1.dist-info/METADATA
myfoobar-0.0.1.dist-info/top_level.txt
myfoobar-0.0.1.dist-info/RECORD
myfoobar-0.0.1.dist-info/WHEEL
